searchkit/__init__.py
searchkit/constraints.py
searchkit/exception.py
searchkit/log.py
searchkit/result.py
searchkit/results_store.py
searchkit/search.py
searchkit/searchdef.py
searchkit/task.py
searchkit/utils.py
searchkit-0.4.3.post6.dist-info/licenses/LICENSE
tests/__init__.py
tests/unit/__init__.py
tests/unit/test_results_store.py
tests/unit/test_search.py
tests/unit/test_search_constraints.py
tests/unit/test_utils.py
tests/unit/utils.py
searchkit-0.4.3.post6.dist-info/METADATA
searchkit-0.4.3.post6.dist-info/WHEEL
searchkit-0.4.3.post6.dist-info/top_level.txt
searchkit-0.4.3.post6.dist-info/RECORD
