Metadata-Version: 2.4
Name: searchkit
Version: 0.4.3.post6
Summary: Python library providing tools to search files in parallel.
Requires-Python: >=3.8
License-File: LICENSE
Requires-Dist: fasteners
Requires-Dist: psutil
Dynamic: license-file
